pecpy/__init__.py
pecpy/core.py
pecpy/gdsutils.py
pecpy/examples/example_calibration.py
pecpy/examples/example_core.py
pecpy/examples/example_gdsutils.py
pecpy/resources/cheese_mini.gds
pecpy/resources/cheese_mini.png
pecpy/resources/cross_mini.png
pecpy-0.7.dist-info/DESCRIPTION.rst
pecpy-0.7.dist-info/METADATA
pecpy-0.7.dist-info/RECORD
pecpy-0.7.dist-info/WHEEL
pecpy-0.7.dist-info/metadata.json
pecpy-0.7.dist-info/top_level.txt
