Metadata-Version: 2.0
Name: pecpy
Version: 0.7
Summary: Optimization-based proximity effect correction
Home-page: https://git.kern.phys.au.dk/SunTune/pecpy
Author: Emil Haldrup Eriksen
Author-email: emher@au.dk
License: MIT
Platform: UNKNOWN
Requires-Dist: opencv-python
Requires-Dist: pillow
Requires-Dist: python-gdsii
Requires-Dist: shapely
Requires-Dist: numpy
Requires-Dist: scipy
